unstructured_client/__init__.py
unstructured_client/_hooks/__init__.py
unstructured_client/_hooks/custom/__init__.py
unstructured_client/_hooks/custom/clean_server_url_hook.py
unstructured_client/_hooks/custom/common.py
unstructured_client/_hooks/custom/form_utils.py
unstructured_client/_hooks/custom/logger_hook.py
unstructured_client/_hooks/custom/pdf_utils.py
unstructured_client/_hooks/custom/request_utils.py
unstructured_client/_hooks/custom/split_pdf_hook.py
unstructured_client/_hooks/custom/validation_errors.py
unstructured_client/_hooks/registration.py
unstructured_client/_hooks/sdkhooks.py
unstructured_client/_hooks/types.py
unstructured_client/_version.py
unstructured_client/basesdk.py
unstructured_client/destinations.py
unstructured_client/general.py
unstructured_client/httpclient.py
unstructured_client/jobs.py
unstructured_client/models/__init__.py
unstructured_client/models/errors/__init__.py
unstructured_client/models/errors/httpvalidationerror.py
unstructured_client/models/errors/no_response_error.py
unstructured_client/models/errors/responsevalidationerror.py
unstructured_client/models/errors/sdkerror.py
unstructured_client/models/errors/servererror.py
unstructured_client/models/errors/unstructuredclienterror.py
unstructured_client/models/operations/__init__.py
unstructured_client/models/operations/cancel_job.py
unstructured_client/models/operations/create_connection_check_destinations.py
unstructured_client/models/operations/create_connection_check_sources.py
unstructured_client/models/operations/create_destination.py
unstructured_client/models/operations/create_job.py
unstructured_client/models/operations/create_source.py
unstructured_client/models/operations/create_workflow.py
unstructured_client/models/operations/delete_destination.py
unstructured_client/models/operations/delete_source.py
unstructured_client/models/operations/delete_workflow.py
unstructured_client/models/operations/download_job_output.py
unstructured_client-0.42.5.dist-info/METADATA
unstructured_client-0.42.5.dist-info/WHEEL
unstructured_client-0.42.5.dist-info/licenses/LICENSE.md
unstructured_client-0.42.5.dist-info/RECORD
